hawkScriptLib/__init__.py
hawkScriptLib/script_tcp_client.py
myhawkscriptlib-0.1.2.dist-info/METADATA
myhawkscriptlib-0.1.2.dist-info/WHEEL
myhawkscriptlib-0.1.2.dist-info/top_level.txt
myhawkscriptlib-0.1.2.dist-info/RECORD
