Metadata-Version: 2.1
Name: myHawkScriptLib
Version: 0.1.2
Summary: This library is used for communication between Hawk script and hz team's GUI PLC driver
Home-page: 
Author: Johnny
Author-email: 13429113807@163.com
Classifier: Programming Language :: Python :: 3
Classifier: License :: OSI Approved :: MIT License
Classifier: Operating System :: OS Independent
Requires-Python: >=3.8
Provides-Extra: dev
Requires-Dist: pytest>=6.0; extra == "dev"
Requires-Dist: twine>=4.0.2; extra == "dev"
Requires-Dist: setuptools>=42.0.0; extra == "dev"
